random_spammer/__init__.py
random_spammer-1.0.3.dist-info/METADATA
random_spammer-1.0.3.dist-info/WHEEL
random_spammer-1.0.3.dist-info/entry_points.txt
random_spammer-1.0.3.dist-info/top_level.txt
random_spammer-1.0.3.dist-info/RECORD
