Metadata-Version: 2.1
Name: random-spammer
Version: 1.0.3
Summary: Collection of functions that can be used in spamming
Home-page: https://github.com/sadiqush/random_spammer
Author: Sadiqush
Author-email: sadiqush@gmail.com
License: MIT
Platform: UNKNOWN
Classifier: License :: OSI Approved :: MIT License
Classifier: Programming Language :: Python :: 3
Classifier: Programming Language :: Python :: 3.9
Requires-Dist: exrex
